bytewax_datadog/__init__.py
bytewax_datadog/inputs/__init__.py
bytewax_datadog/inputs/logs.py
bytewax_datadog/outputs/__init__.py
bytewax_datadog/outputs/logs.py
bytewax_datadog-0.1.1.dist-info/METADATA
bytewax_datadog-0.1.1.dist-info/WHEEL
bytewax_datadog-0.1.1.dist-info/RECORD
