Metadata-Version: 2.4
Name: bytewax-datadog
Version: 0.1.1
Summary: Datadog connectors for Bytewax
Project-URL: Repository, https://github.com/imnotjames/bytewax-datadog.git
Project-URL: Issues, https://github.com/imnotjames/bytewax-datadog/issues
Author-email: James Ward <james@notjam.es>
License-Expression: MIT
Keywords: bytewax,datadog
Requires-Python: >=3.12
Requires-Dist: bytewax>=0.21.1
Requires-Dist: datadog-api-client>=2.33.1
